LICENSE
MANIFEST.in
README.rst
requirements.txt
setup.cfg
setup.py
lyrico/__init__.py
lyrico/__main__.py
lyrico/audio_format_keys.py
lyrico/config.ini
lyrico/config.py
lyrico/docopt.py
lyrico/helper.py
lyrico/lyrico.py
lyrico/song.py
lyrico/song_helper.py
lyrico.egg-info/PKG-INFO
lyrico.egg-info/SOURCES.txt
lyrico.egg-info/dependency_links.txt
lyrico.egg-info/entry_points.txt
lyrico.egg-info/top_level.txt
lyrico/lyrico_sources/__init__.py
lyrico/lyrico_sources/az_lyrics.py
lyrico/lyrico_sources/build_requests.py
lyrico/lyrico_sources/lyric_wikia.py
lyrico/lyrico_sources/lyrics_helper.py
lyrico/lyrico_sources/lyrics_n_music.py
lyrico/lyrico_sources/lyricsmode.py
lyrico/lyrico_sources/musix_match.py